pomodoro/__init__.py
pomodoro/pomodoro.py
pomodorobot-1.0.1.dist-info/LICENSE
pomodorobot-1.0.1.dist-info/METADATA
pomodorobot-1.0.1.dist-info/WHEEL
pomodorobot-1.0.1.dist-info/entry_points.txt
pomodorobot-1.0.1.dist-info/top_level.txt
pomodorobot-1.0.1.dist-info/RECORD
