Metadata-Version: 2.1
Name: pomodorobot
Version: 1.0.1
Summary: This is a very simple CLI pomodoro timer for focusing
Home-page: https://github.com/brynphillips/pomodorobot
Author: Bryn Phillips
Author-email: brynphillips1@gmail.com
License: MIT
Platform: UNKNOWN
Classifier: License :: OSI Approved :: MIT License
